README.txt
setup.cfg
setup.py
docs/HISTORY.txt
docs/INSTALL.txt
docs/LICENSE.GPL
docs/LICENSE.txt
easyshop/__init__.py
easyshop.kss.egg-info/PKG-INFO
easyshop.kss.egg-info/SOURCES.txt
easyshop.kss.egg-info/dependency_links.txt
easyshop.kss.egg-info/entry_points.txt
easyshop.kss.egg-info/namespace_packages.txt
easyshop.kss.egg-info/not-zip-safe
easyshop.kss.egg-info/requires.txt
easyshop.kss.egg-info/top_level.txt
easyshop/kss/__init__.py
easyshop/kss/catalog.py
easyshop/kss/configure.zcml
easyshop/kss/easyshop.kss
easyshop/kss/formatter.py
easyshop/kss/profiles.zcml
easyshop/kss/snippets.py
easyshop/kss/customers/__init__.py
easyshop/kss/customers/address.py
easyshop/kss/customers/configure.zcml
easyshop/kss/customers/snippets.py
easyshop/kss/profiles/__init__.py
easyshop/kss/profiles/default/kssregistry.xml